.gitignore
.travis.yml
AUTHORS
CHANGELOG
COPYING.LESSER
Jenkinsfile
LICENSE
MANIFEST.in
README.md
requirements.txt
setup.cfg
setup.py
tests/pytest.ini
tests/wasp_c_extensions_cmcqueue_test.py
tests/wasp_c_extensions_ev_loop_test.py
tests/wasp_c_extensions_queue_test.py
tests/wasp_c_extensions_threads_test.py
wasp_c_extensions/__init__.py
wasp_c_extensions/common.h
wasp_c_extensions/module_common.h
wasp_c_extensions/static_functions.h
wasp_c_extensions/version.py
wasp_c_extensions.egg-info/PKG-INFO
wasp_c_extensions.egg-info/SOURCES.txt
wasp_c_extensions.egg-info/dependency_links.txt
wasp_c_extensions.egg-info/not-zip-safe
wasp_c_extensions.egg-info/requires.txt
wasp_c_extensions.egg-info/top_level.txt
wasp_c_extensions/__pycache__/__init__.cpython-35.pyc
wasp_c_extensions/__pycache__/__init__.cpython-36.pyc
wasp_c_extensions/__pycache__/__init__.cpython-39.pyc
wasp_c_extensions/__pycache__/__init__.pypy3-60.pyc
wasp_c_extensions/__pycache__/version.cpython-35.pyc
wasp_c_extensions/__pycache__/version.cpython-36.pyc
wasp_c_extensions/__pycache__/version.pypy3-60.pyc
wasp_c_extensions/_cmcqueue/cmcqueue.cpp
wasp_c_extensions/_cmcqueue/cmcqueue.hpp
wasp_c_extensions/_cmcqueue/cmcqueue_module.c
wasp_c_extensions/_cmcqueue/cmcqueue_wrapper.cpp
wasp_c_extensions/_cmcqueue/cmcqueue_wrapper.h
wasp_c_extensions/_ev_loop/ev_loop.cpp
wasp_c_extensions/_ev_loop/ev_loop.hpp
wasp_c_extensions/_ev_loop/ev_loop_module.c
wasp_c_extensions/_ev_loop/ev_loop_wrapper.cpp
wasp_c_extensions/_ev_loop/ev_loop_wrapper.h
wasp_c_extensions/_queue/mcqueue.c
wasp_c_extensions/_queue/mcqueue.h
wasp_c_extensions/_queue/queue_module.c
wasp_c_extensions/_queue/subscriber.c
wasp_c_extensions/_queue/subscriber.h
wasp_c_extensions/_threads/atomic.c
wasp_c_extensions/_threads/atomic.h
wasp_c_extensions/_threads/event.cpp
wasp_c_extensions/_threads/event.hpp
wasp_c_extensions/_threads/event_wrapper.cpp
wasp_c_extensions/_threads/event_wrapper.h
wasp_c_extensions/_threads/module_functions.h
wasp_c_extensions/_threads/threads_module.c