Metadata-Version: 2.1
Name: wasp-c-extensions
Version: 0.0.2.9
Summary: A library with bunch of CPython extensions
Home-page: https://github.com/a1ezzz/wasp-c-extensions
Author: Ildar Gafurov
Author-email: dev@binblob.com
Maintainer: Ildar Gafurov
Maintainer-email: dev@binblob.com
License: GNU Lesser General Public License v3
Keywords: wasp c-extensions threading threads
Platform: UNKNOWN
Classifier: Development Status :: 2 - Pre-Alpha
Classifier: Intended Audience :: Developers
Classifier: License :: OSI Approved :: GNU General Public License v3 (GPLv3)
Classifier: Operating System :: OS Independent
Classifier: Programming Language :: Python
Classifier: Programming Language :: Python :: 3.6
Classifier: Programming Language :: Python :: 3.7
Classifier: Programming Language :: Python :: 3.8
Classifier: Programming Language :: Python :: 3.9
Classifier: Programming Language :: Python :: 3.10
Classifier: Programming Language :: Python :: 3 :: Only
Classifier: Programming Language :: Python :: Implementation :: CPython
Classifier: Programming Language :: Python :: Implementation :: PyPy
Classifier: Topic :: Software Development :: Libraries
Classifier: Topic :: Software Development :: Libraries :: Python Modules
Provides-Extra: dev
Provides-Extra: test
Provides-Extra: all
License-File: LICENSE
License-File: COPYING.LESSER
License-File: AUTHORS
